{
	"configurations" : 
	[
		{
			"directories" : 
			[
				{
					"build" : ".",
					"hasInstallRule" : true,
					"jsonFile" : "directory-.-2ab04600410133f71ae3.json",
					"minimumCMakeVersion" : 
					{
						"string" : "3.20"
					},
					"projectIndex" : 0,
					"source" : ".",
					"targetIndexes" : 
					[
						0,
						1
					]
				}
			],
			"name" : "",
			"projects" : 
			[
				{
					"directoryIndexes" : 
					[
						0
					],
					"name" : "justina_description",
					"targetIndexes" : 
					[
						0,
						1
					]
				}
			],
			"targets" : 
			[
				{
					"directoryIndex" : 0,
					"id" : "justina_description_uninstall::@6890427a1f51a3e7e1df",
					"jsonFile" : "target-justina_description_uninstall-6eb35d40662bc5605f67.json",
					"name" : "justina_description_uninstall",
					"projectIndex" : 0
				},
				{
					"directoryIndex" : 0,
					"id" : "uninstall::@6890427a1f51a3e7e1df",
					"jsonFile" : "target-uninstall-e973dd8bb46573cec058.json",
					"name" : "uninstall",
					"projectIndex" : 0
				}
			]
		}
	],
	"kind" : "codemodel",
	"paths" : 
	{
		"build" : "/home/christopher/Mobile-Robots-2026-1/build/justina_description",
		"source" : "/home/christopher/Mobile-Robots-2026-1/ros2_ws/src/hardware/justina_description"
	},
	"version" : 
	{
		"major" : 2,
		"minor" : 6
	}
}
